pygo_tools/__init__.py
pygo_tools/backend.py
pygo_tools/build_ffi.py
pygo_tools/config.py
pygo_tools/setup.py
pygo_tools/util/__init__.py
pygo_tools/util/monkey_patch.py
pygo_tools/util/pathlib_util.py
pygo_tools-0.1.8.dist-info/METADATA
pygo_tools-0.1.8.dist-info/WHEEL
pygo_tools-0.1.8.dist-info/entry_points.txt
pygo_tools-0.1.8.dist-info/top_level.txt
pygo_tools-0.1.8.dist-info/RECORD
