Metadata-Version: 2.1
Name: pygo-tools
Version: 0.1.8
Summary: Simplify Python-Go integration for Libraries with Precompiled Extensions
Author-email: Rajan Khullar <rkhullar03@gmail.com>
License: MIT NON-AI License
Project-URL: Repository, https://github.com/rkhullar/python-libraries/tree/main/pygo-tools
Keywords: python,golang,cffi
Requires-Python: <4.0,>=3.10
Requires-Dist: build
Requires-Dist: setuptools
Requires-Dist: wheel
Requires-Dist: toml
Requires-Dist: cffi
